proton/apps.py
proton/__init__.py
proton/templates/proton/bootstrap.html
proton/templates/proton/material.html
proton/templates/proton/metro.html
proton/templates/proton/semantic.html
proton/static/proton/jquery-3.1.0.js
proton/static/proton/bootstrap-3.3.7/LICENSE
proton/static/proton/bootstrap-3.3.7/css/bootstrap.min.css
proton/static/proton/bootstrap-3.3.7/js/bootstrap.min.js
proton/static/proton/bootstrap-3.3.7/fonts/glyphicons-halflings-regular.woff
proton/static/proton/bootstrap-3.3.7/fonts/glyphicons-halflings-regular.ttf
proton/static/proton/bootstrap-3.3.7/fonts/glyphicons-halflings-regular.svg
proton/static/proton/bootstrap-3.3.7/fonts/glyphicons-halflings-regular.woff2
proton/static/proton/bootstrap-3.3.7/fonts/glyphicons-halflings-regular.eot
proton/static/proton/materialize/LICENSE
proton/static/proton/materialize/css/materialize.min.css
proton/static/proton/materialize/js/materialize.min.js
proton/static/proton/materialize/fonts/roboto/Roboto-Thin.woff
proton/static/proton/materialize/fonts/roboto/Roboto-Light.ttf
proton/static/proton/materialize/fonts/roboto/Roboto-Regular.woff
proton/static/proton/materialize/fonts/roboto/Roboto-Bold.woff2
proton/static/proton/materialize/fonts/roboto/Roboto-Regular.woff2
proton/static/proton/materialize/fonts/roboto/Roboto-Thin.eot
proton/static/proton/materialize/fonts/roboto/Roboto-Light.woff
proton/static/proton/materialize/fonts/roboto/Roboto-Bold.ttf
proton/static/proton/materialize/fonts/roboto/Roboto-Thin.ttf
proton/static/proton/materialize/fonts/roboto/Roboto-Regular.eot
proton/static/proton/materialize/fonts/roboto/Roboto-Medium.eot
proton/static/proton/materialize/fonts/roboto/Roboto-Light.eot
proton/static/proton/materialize/fonts/roboto/Roboto-Regular.ttf
proton/static/proton/materialize/fonts/roboto/Roboto-Bold.eot
proton/static/proton/materialize/fonts/roboto/Roboto-Light.woff2
proton/static/proton/materialize/fonts/roboto/Roboto-Medium.woff
django_proton-1.0.0.dist-info/DESCRIPTION.rst
django_proton-1.0.0.dist-info/METADATA
django_proton-1.0.0.dist-info/metadata.json
django_proton-1.0.0.dist-info/RECORD
django_proton-1.0.0.dist-info/WHEEL
django_proton-1.0.0.dist-info/top_level.txt
